l0n0lutils/__init__.py
l0n0lutils/async_runner.py
l0n0lutils/dbmysql.py
l0n0lutils/files.py
l0n0lutils/funcs.py
l0n0lutils/mutiprocess_runner.py
l0n0lutils-1.0.14.dist-info/LICENSE
l0n0lutils-1.0.14.dist-info/METADATA
l0n0lutils-1.0.14.dist-info/WHEEL
l0n0lutils-1.0.14.dist-info/entry_points.txt
l0n0lutils-1.0.14.dist-info/top_level.txt
l0n0lutils-1.0.14.dist-info/RECORD
