Metadata-Version: 2.1
Name: l0n0lutils
Version: 1.0.14
Summary: 一些好用的函数和类
Home-page: https://gitee.com/l00n00l/l0n0lutils
Author: l0n0l
Author-email: 1038352856@qq.com
License: UNKNOWN
Platform: UNKNOWN
Classifier: Programming Language :: Python :: 3
Classifier: License :: OSI Approved :: MIT License
Classifier: Operating System :: OS Independent
Requires-Dist: xlrd (==1.2.0)
Requires-Dist: pyyaml
